pyxll_openbb/__init__.py
pyxll_openbb/generate_wrappers.py
pyxll_openbb/obbject.py
pyxll_openbb/pyxll.py
pyxll_openbb/ribbon.py
pyxll_openbb/wrappers.py
pyxll_openbb/resources/ribbon.xml
pyxll_openbb/resources/update.png
pyxll_openbb-0.0.1.dist-info/LICENSE.md
pyxll_openbb-0.0.1.dist-info/METADATA
pyxll_openbb-0.0.1.dist-info/WHEEL
pyxll_openbb-0.0.1.dist-info/entry_points.txt
pyxll_openbb-0.0.1.dist-info/top_level.txt
pyxll_openbb-0.0.1.dist-info/RECORD
