Metadata-Version: 2.1
Name: pyxll-openbb
Version: 0.0.1
Summary: PyXLL wrappers for OpenBB SDK v4
Author-email: Tony Roberts <tony@pyxll.com>
Classifier: Programming Language :: Python :: 3
Classifier: License :: OSI Approved :: MIT License
Classifier: Operating System :: OS Independent
License-File: LICENSE.md
Requires-Dist: pyxll >=5.6.4
Requires-Dist: openbb >=4.0.0a
